kge/__init__.py
kge/engine.py
kge/audio/__init__.py
kge/audio/audio_manager.py
kge/audio/audio_source.py
kge/audio/events.py
kge/audio/sound.py
kge/clocks/__init__.py
kge/clocks/updater.py
kge/core/__init__.py
kge/core/behavior_manager.py
kge/core/behaviour.py
kge/core/camera.py
kge/core/color.py
kge/core/component.py
kge/core/component_system.py
kge/core/constants.py
kge/core/entity.py
kge/core/entity_manager.py
kge/core/event_dispatcher.py
kge/core/eventlib.py
kge/core/events.py
kge/core/exceptions.py
kge/core/logger.py
kge/core/preferences.py
kge/core/scene.py
kge/core/service.py
kge/core/service_provider.py
kge/core/system.py
kge/core/transform.py
kge/docs/__init__.py
kge/editor/__init__.py
kge/examples/__init__.py
kge/examples/camera_controller.py
kge/examples/pong.py
kge/examples/space_invaders.py
kge/examples/assets/__init__.py
kge/extra/__init__.py
kge/extra/linux64/__init__.py
kge/extra/linux64/Box2D/Box2D.py
kge/extra/linux64/Box2D/_Box2D.cpython-36m-x86_64-linux-gnu.so
kge/extra/linux64/Box2D/__init__.py
kge/extra/linux64/Box2D/b2/__init__.py
kge/extra/win32/__init__.py
kge/extra/win32/Box2D/Box2D.py
kge/extra/win32/Box2D/_Box2D.cp37-win32.pyd
kge/extra/win32/Box2D/__init__.py
kge/extra/win32/Box2D/b2/__init__.py
kge/extra/win64/__init__.py
kge/extra/win64/Box2D/Box2D.py
kge/extra/win64/Box2D/_Box2D.cp37-win_amd64.pyd
kge/extra/win64/Box2D/__init__.py
kge/extra/win64/Box2D/b2/__init__.py
kge/graphics/__init__.py
kge/graphics/animated_sprite.py
kge/graphics/animation.py
kge/graphics/animator.py
kge/graphics/image.py
kge/graphics/render_component.py
kge/graphics/renderer.py
kge/graphics/sprite.py
kge/graphics/sprite_renderer.py
kge/graphics/tile_renderer.py
kge/graphics/tilegrid.py
kge/inputs/__init__.py
kge/inputs/input.py
kge/inputs/input_manager.py
kge/inputs/keys.py
kge/inputs/mouse.py
kge/physics/__init__.py
kge/physics/colliders.py
kge/physics/events.py
kge/physics/fixed_updater.py
kge/physics/joints.py
kge/physics/physics_manager.py
kge-1.0.1.dist-info/LICENSE
kge-1.0.1.dist-info/METADATA
kge-1.0.1.dist-info/WHEEL
kge-1.0.1.dist-info/top_level.txt
kge-1.0.1.dist-info/zip-safe
kge-1.0.1.dist-info/RECORD
