Metadata-Version: 2.1
Name: kge
Version: 1.0.1
Summary: A 2D Game Engine Written in Python, running in Python and For Python Game Developpers
Home-page: https://github.com/Fredkiss3/kge
Author: Fredhel KISSIE
Author-email: fredkiss3@gmail.com
License: UNKNOWN
Platform: UNKNOWN
Classifier: Intended Audience :: Developers
Classifier: Programming Language :: Python :: 3.7
Classifier: Programming Language :: Python :: 3.6
Classifier: Topic :: Games/Entertainment
Classifier: Topic :: Software Development :: Libraries :: Python Modules
Requires-Python: >= 3.6, < 3.8
Requires-Dist: dataclasses (==0.6)
Requires-Dist: Pillow (==7.0.0)
Requires-Dist: pyglet (==1.5.0)
Requires-Dist: pyglet-ffmpeg2 (==0.1.17)
